Metadata-Version: 1.0
Name: datasalgo
Version: 0.1.1
Summary: Data Structures and Algorithms package Package
Home-page: UNKNOWN
Author: UNKNOWN
Author-email: UNKNOWN
License: UNKNOWN
Platform: UNKNOWN
